supekku/AGENTS.md
supekku/INIT.md
supekku/__init__.py
supekku/about/README.md
supekku/about/RUN.md
supekku/about/backlog.md
supekku/about/frontmatter-schema.md
supekku/about/glossary.md
supekku/about/lifecycle.md
supekku/about/processes.md
supekku/agents/init.md
supekku/claude.commands/complete-initial-spec.md
supekku/claude.commands/supekku.backfill.md
supekku/claude.commands/supekku.delta_plan.md
supekku/claude.commands/supekku.next-phase.md
supekku/claude.commands/supekku.revision_block.md
supekku/claude.commands/supekku.spec_backfill.md
supekku/claude.commands/supekku.specify.md
supekku/claude.commands/supekku.template.md
supekku/cli/__init__.py
supekku/cli/backfill.py
supekku/cli/backfill_test.py
supekku/cli/common.py
supekku/cli/complete.py
supekku/cli/create.py
supekku/cli/create_test.py
supekku/cli/list.py
supekku/cli/list_test.py
supekku/cli/main.py
supekku/cli/schema.py
supekku/cli/schema_test.py
supekku/cli/show.py
supekku/cli/show_test.py
supekku/cli/sync.py
supekku/cli/sync_test.py
supekku/cli/test_cli.py
supekku/cli/workspace.py
supekku/scripts/__init__.py
supekku/scripts/change_registry.py
supekku/scripts/complete_delta.py
supekku/scripts/create_delta.py
supekku/scripts/create_new_spec.py
supekku/scripts/create_requirement.py
supekku/scripts/create_revision.py
supekku/scripts/decision_registry.py
supekku/scripts/install.py
supekku/scripts/list_changes.py
supekku/scripts/list_deltas.py
supekku/scripts/list_specs.py
supekku/scripts/migrate_stub_status.py
supekku/scripts/requirements.py
supekku/scripts/sync_specs.py
supekku/scripts/validate_revision_blocks.py
supekku/scripts/validate_workspace.py
supekku/scripts/backlog/__init__.py
supekku/scripts/backlog/append.py
supekku/scripts/backlog/create_entry.py
supekku/scripts/cli/__init__.py
supekku/scripts/cli/ast_doc_generator.py
supekku/scripts/cli/deterministic_ast_doc_generator.py
supekku/scripts/lib/TODO.md
supekku/scripts/lib/YAML_BLOCKS_ANALYSIS.md
supekku/scripts/lib/__init__.py
spec_driver-0.4.5.dist-info/METADATA
spec_driver-0.4.5.dist-info/WHEEL
spec_driver-0.4.5.dist-info/entry_points.txt
spec_driver-0.4.5.dist-info/licenses/LICENSE
spec_driver-0.4.5.dist-info/RECORD
