Metadata-Version: 2.4
Name: spec-driver
Version: 0.4.5
Summary: Specification-driven development toolkit with multi-language spec sync and documentation generation
Project-URL: Homepage, https://github.com/davidlee/spec-driver
Project-URL: Repository, https://github.com/davidlee/spec-driver
Project-URL: Issues, https://github.com/davidlee/spec-driver/issues
Project-URL: Website, https://supekku.dev/
Author-email: David Lee <dav@davlee.com>
License: MIT
License-File: LICENSE
Keywords: adr,architecture-decision-records,documentation,spec-sync,specification
Classifier: Development Status :: 3 - Alpha
Classifier: Intended Audience :: Developers
Classifier: License :: OSI Approved :: MIT License
Classifier: Programming Language :: Python :: 3
Classifier: Programming Language :: Python :: 3.10
Classifier: Programming Language :: Python :: 3.11
Classifier: Programming Language :: Python :: 3.12
Classifier: Programming Language :: Python :: 3.13
Classifier: Topic :: Software Development :: Documentation
Classifier: Topic :: Software Development :: Libraries :: Python Modules
Requires-Python: >=3.10
Requires-Dist: jinja2>=3.1.0
Requires-Dist: python-frontmatter>=1.1.0
Requires-Dist: pyyaml>=6.0.3
Requires-Dist: typer>=0.15.0
